MANIFEST.in
README.rst
setup.py
sphinxcontrib/__init__.py
sphinxcontrib/jsoncall/__init__.py
sphinxcontrib/jsoncall/_escaping.py
sphinxcontrib/jsoncall/_static/__init__.py
sphinxcontrib/jsoncall/_static/jsoncall.css
sphinxcontrib/jsoncall/_static/jsoncall.js
sphinxcontrib/tgjsonautodoc/__init__.py
sphinxcontrib_jsoncall.egg-info/PKG-INFO
sphinxcontrib_jsoncall.egg-info/SOURCES.txt
sphinxcontrib_jsoncall.egg-info/dependency_links.txt
sphinxcontrib_jsoncall.egg-info/namespace_packages.txt
sphinxcontrib_jsoncall.egg-info/not-zip-safe
sphinxcontrib_jsoncall.egg-info/requires.txt
sphinxcontrib_jsoncall.egg-info/top_level.txt