Metadata-Version: 1.0
Name: sphinxcontrib-jsoncall
Version: 0.2
Summary: Sphinx extension that adds a simple button to perform test calls to JSON based apis
Home-page: https://github.com/amol-/sphinxcontrib.jsoncall
Author: Alessandro Molina
Author-email: alessandro.molina@axant.it
License: MIT
Platform: UNKNOWN
